LICENSE_code
LICENSE_doc
MANIFEST.in
README.md
pyproject.toml
requirements.txt
setup.py
doc/img/benchmark_error_HH_PT_vs_HH_OURS.png
doc/img/benchmark_error_HH_PT_vs_HH_OURS_64.png
doc/img/benchmark_error_MEXP_vs_HH_OURS.png
doc/img/benchmark_speed_HH_PT_vs_HH_OURS.png
doc/img/benchmark_speed_HH_PT_vs_HH_OURS_64.png
doc/img/benchmark_speed_MEXP_vs_HH_OURS.png
doc/img/formula_err.png
doc/img/householder.png
doc/img/logo.png
doc/img/logo_small.png
tests/benchmark_all.py
tests/benchmark_one.py
tests/benchmark_plot_results.py
tests/reference_orgqr.py
tests/requirements_test.txt
tests/test.py
torch_householder/__init__.py
torch_householder/householder.cpp
torch_householder/householder.py
torch_householder/version.py
torch_householder.egg-info/PKG-INFO
torch_householder.egg-info/SOURCES.txt
torch_householder.egg-info/dependency_links.txt
torch_householder.egg-info/requires.txt
torch_householder.egg-info/top_level.txt