Metadata-Version: 2.1
Name: torch-householder
Version: 1.0.1
Summary: Efficient Householder Transformation in PyTorch
Home-page: https://www.github.com/toshas/torch-householder
Author: Anton Obukhov
License: BSD
Keywords: pytorch,householder,orgqr,householer_product,efficient,differentiable,orthogonal,transformation,unitary,matrices,stiefel,manifold
Platform: UNKNOWN
Requires-Python: >=3.6
License-File: LICENSE_code
License-File: LICENSE_doc
